MANIFEST.in
README.md
setup.py
bin/calibrate_cyberglove.py
bin/fit_cyberglove_mapping.py
bin/glove_sensors.py
bin/hand_joints.py
bin/show_calibrated.py
cyberglove/__init__.py
cyberglove/const.py
cyberglove/driver.py
cyberglove/mapped_viewer.py
cyberglove/mapping.py
cyberglove/prescribed_viewer.py
cyberglove.egg-info/PKG-INFO
cyberglove.egg-info/SOURCES.txt
cyberglove.egg-info/dependency_links.txt
cyberglove.egg-info/requires.txt
cyberglove.egg-info/top_level.txt