Metadata-Version: 1.0
Name: cyberglove
Version: 0.2.8
Summary: Communicate with cyberglove from python
Home-page: UNKNOWN
Author: Alex Ray
Author-email: aray@openai.com
License: UNKNOWN
Platform: UNKNOWN
